edc_protocol/__init__.py
edc_protocol/address.py
edc_protocol/apps.py
edc_protocol/middleware.py
edc_protocol/navbars.py
edc_protocol/research_protocol_config.py
edc_protocol/system_checks.py
edc_protocol/urls.py
edc_protocol/validators.py
edc_protocol/view_mixins.py
edc_protocol/views.py
edc_protocol/locale/sw/LC_MESSAGES/django.mo
edc_protocol/locale/sw/LC_MESSAGES/django.po
edc_protocol/templates/edc_protocol/home.html
edc_protocol/tests/__init__.py
edc_protocol/tests/test_settings.py
edc_protocol/tests/tests.py
edc_protocol/tests/urls.py
edc_protocol/tests/etc/user-aes-local.key
edc_protocol/tests/etc/user-aes-restricted.key
edc_protocol/tests/etc/user-rsa-local-private.pem
edc_protocol/tests/etc/user-rsa-local-public.pem
edc_protocol/tests/etc/user-rsa-restricted-private.pem
edc_protocol/tests/etc/user-rsa-restricted-public.pem
edc_protocol/tests/etc/user-salt-local.key
edc_protocol/tests/etc/user-salt-restricted.key
edc_protocol-1.0.1.dist-info/licenses/AUTHORS.rst
edc_protocol-1.0.1.dist-info/licenses/LICENSE
edc_protocol-1.0.1.dist-info/METADATA
edc_protocol-1.0.1.dist-info/WHEEL
edc_protocol-1.0.1.dist-info/top_level.txt
edc_protocol-1.0.1.dist-info/RECORD
